{
    "version": 7,
    "configurePresets": [
        {
            "name": "debug",
            "displayName": "Debug",
            "binaryDir": "${sourceDir}/build",
            "environment": {
                "CC": "clang",
                "CXX": "clang++"
            },
            "cacheVariables": {
                "CMAKE_BUILD_TYPE": "Debug",
                "BUILD_SHARED_LIBS": true
            },
            "generator": "Ninja"
        }
    ],
    "buildPresets": [
        {
            "name": "debug",
            "displayName": "Debug",
            "configurePreset": "debug"
        }
    ]
}
